jamaibase/__init__.py
jamaibase/client.py
jamaibase/protocol.py
jamaibase/version.py
jamaibase/types/__init__.py
jamaibase/types/billing.py
jamaibase/types/common.py
jamaibase/types/compat.py
jamaibase/types/conversation.py
jamaibase/types/db.py
jamaibase/types/file.py
jamaibase/types/gen_table.py
jamaibase/types/legacy.py
jamaibase/types/lm.py
jamaibase/types/logs.py
jamaibase/types/mcp.py
jamaibase/types/model.py
jamaibase/types/telemetry.py
jamaibase/utils/__init__.py
jamaibase/utils/background_loop.py
jamaibase/utils/dates.py
jamaibase/utils/exceptions.py
jamaibase/utils/io.py
jamaibase/utils/types.py
jamaibase/utils/versioning.py
jamaibase-1.0.3.dist-info/METADATA
jamaibase-1.0.3.dist-info/WHEEL
jamaibase-1.0.3.dist-info/top_level.txt
jamaibase-1.0.3.dist-info/RECORD
