Metadata-Version: 2.4
Name: jamaibase
Version: 1.0.3
Summary: JamAI Base: Let Your Database Orchestrate LLMs and RAG
License-Expression: Apache-2.0
Classifier: Development Status :: 3 - Alpha
Classifier: Programming Language :: Python :: 3 :: Only
Classifier: Intended Audience :: Information Technology
Classifier: Operating System :: Unix
Requires-Python: >=3.10
Requires-Dist: filetype~=1.2
Requires-Dist: httpx>=0.25.0
Requires-Dist: loguru>=0.7.2
Requires-Dist: natsort[fast]~=8.4
Requires-Dist: numpy<2.0.0,>=1.26.0
Requires-Dist: orjson~=3.9
Requires-Dist: pandas
Requires-Dist: Pillow>=10.0
Requires-Dist: pydantic-extra-types~=2.9
Requires-Dist: pydantic-settings~=2.4
Requires-Dist: pydantic[email,timezone]~=2.10
Requires-Dist: pyyaml~=6.0
Requires-Dist: toml~=0.10.2
Requires-Dist: typing_extensions~=4.10
Requires-Dist: uuid-utils~=0.9.0
Requires-Dist: uuid7~=0.1.0
Provides-Extra: lint
Requires-Dist: ruff~=0.12.9; extra == "lint"
Provides-Extra: test
Requires-Dist: flaky~=3.8.1; extra == "test"
Requires-Dist: locust~=2.39.1; extra == "test"
Requires-Dist: mypy~=1.11.1; extra == "test"
Requires-Dist: pytest-asyncio>=0.23.8; extra == "test"
Requires-Dist: pytest-cov~=5.0.0; extra == "test"
Requires-Dist: pytest-timeout>=2.3.1; extra == "test"
Requires-Dist: pytest~=8.2.2; extra == "test"
Requires-Dist: sphinx-copybutton~=0.5.2; extra == "test"
Requires-Dist: sphinx>=7.0.0; extra == "test"
Requires-Dist: sphinx_rtd_theme~=2.0.0; extra == "test"
Provides-Extra: build
Requires-Dist: build; extra == "build"
Requires-Dist: twine; extra == "build"
Provides-Extra: all
Requires-Dist: jamaibase[build,docs,lint,test]; extra == "all"
